setup.py
deepnet/__init__.py
deepnet/layers.py
deepnet/models.py
deepnet/net.py
deepnet/visualization.py
deepnet.egg-info/PKG-INFO
deepnet.egg-info/SOURCES.txt
deepnet.egg-info/dependency_links.txt
deepnet.egg-info/not-zip-safe
deepnet.egg-info/top_level.txt