Metadata-Version: 1.0
Name: deepnet
Version: 0.5
Summary: package for deep learning
Home-page: https://github.com/leovetter/DeepNet
Author: Léo Vetter
Author-email: vetter.leo@gmail.com
License: UNKNOWN
Platform: UNKNOWN
